Metadata-Version: 2.1
Name: sfutilpsg
Version: 0.1.4
Summary: A utility for managing Salesforce permissions and relationships
Home-page: https://github.com/mohan-chinnappan-n/sfutilpsg
Author: mohan chinnappan
Author-email: mohan.chinnappan.n5@gmail.com
License: MIT
Requires-Dist: requests
Requires-Dist: graphviz
